asgi_cors.py
asgi_cors_graphql-0.3.dist-info/LICENSE
asgi_cors_graphql-0.3.dist-info/METADATA
asgi_cors_graphql-0.3.dist-info/WHEEL
asgi_cors_graphql-0.3.dist-info/top_level.txt
asgi_cors_graphql-0.3.dist-info/RECORD
