Metadata-Version: 2.1
Name: asgi-cors-graphql
Version: 0.3
Summary: ASGI middleware for applying CORS headers to an ASGI application
Home-page: https://github.com/simonw/asgi-cors
Author: Simon Willison
License: Apache License, Version 2.0
Platform: UNKNOWN
License-File: LICENSE
Provides-Extra: test
Requires-Dist: pytest ; extra == 'test'
Requires-Dist: pytest-asyncio ; extra == 'test'
Requires-Dist: asgiref (==3.1.2) ; extra == 'test'
